epyb/__init__.py
epyb/compress.py
epyb/create.py
epyb/route.py
epyb/search.py
epyb/string_lib.py
epyb/text_to_md.py
epyb-0.1.7.dist-info/DESCRIPTION.rst
epyb-0.1.7.dist-info/METADATA
epyb-0.1.7.dist-info/RECORD
epyb-0.1.7.dist-info/WHEEL
epyb-0.1.7.dist-info/metadata.json
epyb-0.1.7.dist-info/top_level.txt
