Metadata-Version: 2.0
Name: epyb
Version: 0.1.7
Summary: A tool which allows you to download books from certain websites and convert to epub for you automatically.
Home-page: https://rioaraki.github.io/epyb
Author: Yue Li
Author-email: yueee.li@mail.utoronto.ca
License: UNKNOWN
Keywords: online book epub converter
Platform: UNKNOWN
Classifier: Development Status :: 3 - Alpha
Classifier: Intended Audience :: Information Technology
Classifier: Topic :: Internet :: WWW/HTTP :: Dynamic Content
Classifier: License :: OSI Approved :: MIT License
Classifier: Programming Language :: Python :: 3.6
Requires-Dist: requests
Requires-Dist: bs4
Requires-Dist: google-api-python-client
